ma_plan_validator/__init__.py
ma_plan_validator/convert_mapddl_to_pddl.py
ma_plan_validator/ma_plan_validator.py
ma_plan_validator-0.0.2.post1.dist-info/LICENSE
ma_plan_validator-0.0.2.post1.dist-info/METADATA
ma_plan_validator-0.0.2.post1.dist-info/WHEEL
ma_plan_validator-0.0.2.post1.dist-info/top_level.txt
ma_plan_validator-0.0.2.post1.dist-info/RECORD
