Metadata-Version: 2.1
Name: ma-plan-validator
Version: 0.0.2.post1
Summary: ma_plan_validator
Home-page: 
Author: Alessandro Trapasso
Author-email: ale.trapasso8@gmail.com
License: APACHE
License-File: LICENSE
